ml_logwriter/__init__.py
ml_logwriter/loggers.py
ml_logwriter-0.2.3.dist-info/.ipynb_checkpoints/PKG-INFO-checkpoint
ml_logwriter-0.2.3.dist-info/.ipynb_checkpoints/SOURCES-checkpoint.txt
ml_logwriter-0.2.3.dist-info/.ipynb_checkpoints/dependency_links-checkpoint.txt
ml_logwriter-0.2.3.dist-info/.ipynb_checkpoints/top_level-checkpoint.txt
ml_logwriter-0.2.3.dist-info/LICENSE
ml_logwriter-0.2.3.dist-info/METADATA
ml_logwriter-0.2.3.dist-info/WHEEL
ml_logwriter-0.2.3.dist-info/top_level.txt
ml_logwriter-0.2.3.dist-info/RECORD
